MANIFEST.in
README.md
setup.py
crax/__init__.py
crax/conf.py
crax/crax.py
crax/data_types.py
crax/exceptions.py
crax/form_data.py
crax/logger.py
crax/request.py
crax/response.py
crax/response_types.py
crax/urls.py
crax/utils.py
crax/views.py
crax.egg-info/PKG-INFO
crax.egg-info/SOURCES.txt
crax.egg-info/dependency_links.txt
crax.egg-info/not-zip-safe
crax.egg-info/requires.txt
crax.egg-info/top_level.txt
crax/auth/__init__.py
crax/auth/authentication.py
crax/auth/middleware.py
crax/auth/models.py
crax/commands/__init__.py
crax/commands/command.py
crax/commands/create_swagger.py
crax/commands/db_create_all.py
crax/commands/db_drop_all.py
crax/commands/history.py
crax/commands/makemigrations.py
crax/commands/migrate.py
crax/database/__init__.py
crax/database/command.py
crax/database/connection.py
crax/database/env.py
crax/database/model.py
crax/middleware/__init__.py
crax/middleware/base.py
crax/middleware/cors.py
crax/middleware/max_body.py
crax/middleware/x_frame.py
crax/swagger/__init__.py
crax/swagger/types.py
crax/swagger/static/favicon-16x16.png
crax/swagger/static/favicon-32x32.png
crax/swagger/static/swagger-ui-bundle.js
crax/swagger/static/swagger-ui-bundle.js.map
crax/swagger/static/swagger-ui-standalone-preset.js
crax/swagger/static/swagger-ui-standalone-preset.js.map
crax/swagger/static/swagger-ui.css
crax/swagger/static/swagger-ui.css.map
crax/swagger/static/swagger-ui.js
crax/swagger/static/swagger-ui.js.map
crax/swagger/static/swagger.json
crax/templates/base.html
crax/templates/default.html
crax/templates/error.html
crax/templates/swagger.html