Metadata-Version: 2.1
Name: crax
Version: 0.1.5
Summary: Python Asynchronous Web Development Switz Knife.
Home-page: https://github.com/ephmann/crax
Author: Eugene Mercousheu
Author-email: crax.info@gmail.com
License: BSD
Platform: UNKNOWN
Classifier: Development Status :: 3 - Alpha
Classifier: Environment :: Web Environment
Classifier: Intended Audience :: Developers
Classifier: License :: OSI Approved :: BSD License
Classifier: Operating System :: OS Independent
Classifier: Topic :: Internet :: WWW/HTTP
Classifier: Programming Language :: Python :: 3
Classifier: Programming Language :: Python :: 3 :: Only
Classifier: Programming Language :: Python :: 3.7
Classifier: Programming Language :: Python :: 3.8
Requires-Python: >=3.7
Provides-Extra: postgresql
Provides-Extra: mysql
Provides-Extra: sqlite
